puripy/__init__.py
puripy/api.py
puripy/security.py
puripy/security_api.py
PuriPy-0.1.0.dist-info/LICENSE
PuriPy-0.1.0.dist-info/METADATA
PuriPy-0.1.0.dist-info/WHEEL
PuriPy-0.1.0.dist-info/top_level.txt
PuriPy-0.1.0.dist-info/RECORD
