Metadata-Version: 2.2
Name: PuriPy
Version: 0.1.0
Summary: A secure Python pre-validation library for AI/ML playgrounds that purifies code.
Home-page: https://github.com/ndavidson19/PyPurify
Author: Nicholas Davidson
Author-email: Nicholas Davidson <nicholas@purify-ai.com>
License: MIT License
Classifier: Programming Language :: Python :: 3
Classifier: License :: OSI Approved :: MIT License
Classifier: Operating System :: OS Independent
Requires-Python: >=3.9
License-File: LICENSE
Requires-Dist: bandit
Requires-Dist: flake8
Dynamic: author
Dynamic: home-page
Dynamic: requires-python
